hashtable_nicolerg/__init__.py
hashtable_nicolerg/hashtable.py
hashtable_nicolerg-1.0.3.dist-info/METADATA
hashtable_nicolerg-1.0.3.dist-info/WHEEL
hashtable_nicolerg-1.0.3.dist-info/licenses/LICENSE
hashtable_nicolerg-1.0.3.dist-info/RECORD
