Metadata-Version: 2.1
Name: hashtable_nicolerg
Version: 1.0.3
Summary: An exercise to learn about hash tables, unit tests, TDD, and Python packages
Project-URL: Docker Image, https://hub.docker.com/repository/docker/nicolerg/python-hashtable
Project-URL: Source Code, https://github.com/nicolerg/python-hashtable/tree/master/hashtable-nicolerg
Project-URL: Guiding Tutorial, https://realpython.com/python-hash-table
Author-email: Nicole Gay <nicole.r.gay@gmail.com>
License-File: LICENSE
Classifier: License :: OSI Approved :: MIT License
Classifier: Operating System :: OS Independent
Classifier: Programming Language :: Python :: 3
Requires-Python: >=3.7
